{
	"info": {
		"_postman_id": "447bf908-501a-4423-b082-9d51ecc9043d",
		"name": "Proyecto Final Backend CoderHouse",
		"schema": "https://schema.getpostman.com/json/collection/v2.1.0/collection.json",
		"_exporter_id": "11304649"
	},
	"item": [
		{
			"name": "products",
			"item": [
				{
					"name": "All products",
					"request": {
						"method": "GET",
						"header": [],
						"url": {
							"raw": "{{localhost}}/api/products/",
							"host": [
								"{{localhost}}"
							],
							"path": [
								"api",
								"products",
								""
							]
						}
					},
					"response": []
				},
				{
					"name": "Product By id",
					"request": {
						"method": "GET",
						"header": [],
						"url": {
							"raw": "{{localhost}}/api/products/:pid",
							"host": [
								"{{localhost}}"
							],
							"path": [
								"api",
								"products",
								":pid"
							],
							"variable": [
								{
									"key": "pid",
									"value": null
								}
							]
						}
					},
					"response": []
				},
				{
					"name": "Add Product",
					"request": {
						"method": "POST",
						"header": [],
						"body": {
							"mode": "raw",
							"raw": "{\r\n    \"title\":\"Producto de prueba\",\r\n    \"description\":\"Este es un producto de prueba\",\r\n    \"code\":\"ABC123\",\r\n    \"price\":250,\r\n    \"status\":true,\r\n    \"stock\":20,\r\n    \"category\":\"prueba\",\r\n    \"thumbnails\":[\r\n        \"https://detallesorballo.com/wp-content/uploads/2020/09/imagen-de-prueba-320x240-1.jpg\"\r\n    ]\r\n}",
							"options": {
								"raw": {
									"language": "json"
								}
							}
						},
						"url": {
							"raw": "{{localhost}}/api/products",
							"host": [
								"{{localhost}}"
							],
							"path": [
								"api",
								"products"
							]
						}
					},
					"response": []
				},
				{
					"name": "Update Product",
					"request": {
						"method": "PUT",
						"header": [],
						"body": {
							"mode": "raw",
							"raw": "{\r\n    \"title\":\"Producto de prueba2\",\r\n    \"price\":450\r\n}",
							"options": {
								"raw": {
									"language": "json"
								}
							}
						},
						"url": {
							"raw": "{{localhost}}/api/products/:pid",
							"host": [
								"{{localhost}}"
							],
							"path": [
								"api",
								"products",
								":pid"
							],
							"variable": [
								{
									"key": "pid",
									"value": null
								}
							]
						}
					},
					"response": []
				},
				{
					"name": "Delete Product",
					"request": {
						"method": "DELETE",
						"header": [],
						"url": {
							"raw": "{{localhost}}/api/products/:pid",
							"host": [
								"{{localhost}}"
							],
							"path": [
								"api",
								"products",
								":pid"
							],
							"variable": [
								{
									"key": "pid",
									"value": null
								}
							]
						}
					},
					"response": []
				}
			]
		},
		{
			"name": "carts",
			"item": [
				{
					"name": "New Cart",
					"request": {
						"method": "POST",
						"header": [],
						"url": {
							"raw": "{{localhost}}/api/carts/",
							"host": [
								"{{localhost}}"
							],
							"path": [
								"api",
								"carts",
								""
							]
						}
					},
					"response": []
				},
				{
					"name": "Get Cart by Id",
					"request": {
						"method": "GET",
						"header": [],
						"url": {
							"raw": "{{localhost}}/api/carts/:cid",
							"host": [
								"{{localhost}}"
							],
							"path": [
								"api",
								"carts",
								":cid"
							],
							"variable": [
								{
									"key": "cid",
									"value": null
								}
							]
						}
					},
					"response": []
				},
				{
					"name": "Add product to cart",
					"request": {
						"method": "POST",
						"header": [],
						"url": {
							"raw": "{{localhost}}/api/carts/:cid/product/:pid",
							"host": [
								"{{localhost}}"
							],
							"path": [
								"api",
								"carts",
								":cid",
								"product",
								":pid"
							],
							"variable": [
								{
									"key": "cid",
									"value": null
								},
								{
									"key": "pid",
									"value": null
								}
							]
						}
					},
					"response": []
				}
			]
		}
	]
}